[{"date":"2023-03-23T08:00:00Z","permalink":"https://swiest.com/pt-br/en/3001700001/","title":"Canva - Canva Create: Brand New Era - Português"},{"date":"2023-03-21T09:00:00Z","permalink":"https://swiest.com/pt-br/3001600001/","title":"NVIDIA - GTC 2023 Keynote with NVIDIA CEO Jensen Huang - Português"},{"date":"2023-01-18T19:00:00Z","permalink":"https://swiest.com/pt-br/3000400018/","title":"Hora de caminhar - Destaques da temporada 1"},{"date":"2023-01-17T19:00:00Z","permalink":"https://swiest.com/pt-br/3000400017/","title":"Hora de caminhar - Hora de caminhar com Nick Jonas"},{"date":"2023-01-16T19:00:00Z","permalink":"https://swiest.com/pt-br/3000400016/","title":"Hora de caminhar - Hora de caminhar com Jane Fonda"},{"date":"2023-01-15T19:00:00Z","permalink":"https://swiest.com/pt-br/3000400015/","title":"Hora de caminhar - Hora de caminhar com Jon M. Chu"},{"date":"2023-01-14T19:00:00Z","permalink":"https://swiest.com/pt-br/3000400014/","title":"Hora de caminhar - Hora de caminhar com Wanda Sykes"},{"date":"2023-01-13T19:00:00Z","permalink":"https://swiest.com/pt-br/3000400013/","title":"Hora de caminhar - Hora de caminhar com Malcolm Gladwell"},{"date":"2023-01-12T19:00:00Z","permalink":"https://swiest.com/pt-br/3000400012/","title":"Hora de caminhar - Hora de caminhar com Kesha"},{"date":"2023-01-11T19:00:00Z","permalink":"https://swiest.com/pt-br/3000400011/","title":"Hora de caminhar - Hora de caminhar com Anthony Ramos"},{"date":"2023-01-10T19:00:00Z","permalink":"https://swiest.com/pt-br/3000400010/","title":"Hora de caminhar - Hora de caminhar com Min Jin Lee"},{"date":"2023-01-09T19:00:00Z","permalink":"https://swiest.com/pt-br/3000400009/","title":"Hora de caminhar - Hora de caminhar com Anderson Cooper"},{"date":"2023-01-08T19:00:00Z","permalink":"https://swiest.com/pt-br/3000400008/","title":"Hora de caminhar - Hora de caminhar com Misty Copeland"},{"date":"2023-01-07T19:00:00Z","permalink":"https://swiest.com/pt-br/3000400007/","title":"Hora de caminhar - Hora de caminhar com Bubba Wallace"},{"date":"2023-01-06T19:00:00Z","permalink":"https://swiest.com/pt-br/3000400006/","title":"Hora de caminhar - Hora de caminhar com Ruby Bridges"},{"date":"2023-01-05T19:00:00Z","permalink":"https://swiest.com/pt-br/3000400005/","title":"Hora de caminhar - Hora de caminhar com Ibram X. Kendi"},{"date":"2023-01-04T19:00:00Z","permalink":"https://swiest.com/pt-br/3000400004/","title":"Hora de caminhar - Hora de caminhar com Shawn Mendes"},{"date":"2023-01-03T19:00:00Z","permalink":"https://swiest.com/pt-br/3000400003/","title":"Hora de caminhar - Hora de caminhar com Uzo Aduba"},{"date":"2023-01-02T19:00:00Z","permalink":"https://swiest.com/pt-br/3000400002/","title":"Hora de caminhar - Hora de caminhar com Draymond Green"},{"date":"2023-01-01T19:00:00Z","permalink":"https://swiest.com/pt-br/3000400001/","title":"Hora de caminhar - Hora de caminhar com Dolly Parton"},{"date":"2022-12-25T10:00:00Z","permalink":"https://swiest.com/pt-br/3000100001/","title":"MrBeast - Sobrevivi 50 Horas na Antártica!"},{"date":"2022-11-02T17:00:00Z","permalink":"https://swiest.com/pt-br/2000100001/","title":"Selena Gomez: Minha Mente e Eu"},{"date":"2022-03-01T18:00:00Z","permalink":"https://swiest.com/pt-br/932203787/","title":"O Caso do Cavalo de Tróia Parte 1 A Carta no Envelope de Papel Pardo"}]